outlier/__init__.py
outlier/outlier.py
outlier_remover_csv-1.0.6.dist-info/LICENSE
outlier_remover_csv-1.0.6.dist-info/METADATA
outlier_remover_csv-1.0.6.dist-info/WHEEL
outlier_remover_csv-1.0.6.dist-info/top_level.txt
outlier_remover_csv-1.0.6.dist-info/RECORD
