Metadata-Version: 2.1
Name: outlier-remover-csv
Version: 1.0.6
Summary: Outlier remover tool
Home-page: https://github.com/NoOne03/outlier_remover.git
Author: Prateek kr Singh
Author-email: prateekkumarsingh3@gmail.com
License: UNKNOWN
Platform: UNKNOWN
Classifier: Programming Language :: Python :: 3
Classifier: License :: OSI Approved :: MIT License
Classifier: Operating System :: OS Independent
Requires-Python: >=3.6
